hummuspy/__init__.py
hummuspy/config.py
hummuspy/core_grn.py
hummuspy/create_multilayer.py
hummuspy/explore_network.py
hummuspy/loader.py
hummuspy-0.1.9.post1.dist-info/licenses/LICENSE
hummuspy-0.1.9.post1.dist-info/METADATA
hummuspy-0.1.9.post1.dist-info/WHEEL
hummuspy-0.1.9.post1.dist-info/top_level.txt
hummuspy-0.1.9.post1.dist-info/RECORD
